[
    {
        "id" : "PingPong",
        "name" : {
            "en" : "Ping-Pong",
            "ru" : "Пинг-Понг",
            "ua" : "Пiнг-Понг"
        },
        "about" : {
            "en" : "Ping pong against a bot",
            "ru" : "Пинг-понг против бота",
            "ua" : "Пiнг-понг проти бота"
        }
    },
    {
        "id" : "Clicker",
        "name" :{
            "en" : "Number Clicker",
            "ru" : "Числовой кликер",
            "ua" : "Числовий клiкер"
        },
        "about" : {
            "en" : "Simple number clicker",
            "ru" : "Простой числовой кликер",
            "ua" : "Звичайний числовий клiкер"
        }
    },
    {
        "id" : "CarDrive",
        "name" :{
            "en" : "Car Drive",
            "ru" : "Гонки на машине",
            "ua" : "Гонки на маншинi"
        },
        "about" : {
            "en" : "Car driving in 2D",
            "ru" : "Гонки на машине в 2Д",
            "ua" : "Гонки на машинi в 2Д"
        }
    }
]